[{"timestamp":"2023-12-01T01:50:12.112Z","count":0,"uniques":0},{"timestamp":"2024-01-01T01:50:12.112Z","count":0,"uniques":0},{"timestamp":"2024-02-01T01:50:12.112Z","count":0,"uniques":0},{"timestamp":"2024-03-01T01:50:12.112Z","count":0,"uniques":0},{"timestamp":"2024-04-01T01:50:12.112Z","count":0,"uniques":0},{"timestamp":"2024-05-01T01:50:12.112Z","count":0,"uniques":0},{"timestamp":"2024-06-01T01:50:12.112Z","count":0,"uniques":0},{"timestamp":"2024-07-01T01:50:12.112Z","count":0,"uniques":0},{"timestamp":"2024-08-01T01:50:12.112Z","count":0,"uniques":0},{"timestamp":"2024-09-01T01:50:12.112Z","count":0,"uniques":0},{"timestamp":"2024-10-01T18:31:01.291Z","count":635,"uniques":117},{"timestamp":"2024-11-01T06:33:54.608Z","count":1129,"uniques":199},{"timestamp":"2024-12-01T01:50:25.412Z","count":642,"uniques":103}]
