[{"timestamp":"2024-12-21T01:39:39.978Z","count":0,"uniques":0},{"timestamp":"2024-12-22T01:47:30.534Z","count":0,"uniques":0},{"timestamp":"2024-12-23T01:43:03.873Z","count":0,"uniques":0},{"timestamp":"2024-12-24T01:40:56.453Z","count":0,"uniques":0},{"timestamp":"2024-12-25T01:39:46.742Z","count":0,"uniques":0},{"timestamp":"2024-12-26T01:40:03.243Z","count":0,"uniques":0},{"timestamp":"2024-12-27T01:40:44.338Z","count":0,"uniques":0},{"timestamp":"2024-12-28T01:38:40.324Z","count":0,"uniques":0}]
